promptius_gui_schema/__init__.py
promptius_gui_schema-2.0.8.dist-info/METADATA
promptius_gui_schema-2.0.8.dist-info/WHEEL
promptius_gui_schema-2.0.8.dist-info/licenses/LICENSE
promptius_gui_schema-2.0.8.dist-info/RECORD
