Metadata-Version: 2.4
Name: promptius-gui-schema
Version: 2.0.8
Summary: Type-safe UI schema definitions for cross-platform UI generation
Project-URL: Homepage, https://github.com/AgentBossMode/promptius-gui
Project-URL: Repository, https://github.com/AgentBossMode/promptius-gui
Project-URL: Documentation, https://github.com/AgentBossMode/promptius-gui#readme
Project-URL: Bug Tracker, https://github.com/AgentBossMode/promptius-gui/issues
Author-email: Kanishk Gupta <51890299+kanishkgupta2000@users.noreply.github.com>
Maintainer-email: Kanishk Gupta <51890299+kanishkgupta2000@users.noreply.github.com>
License: MIT License
License-File: LICENSE
Keywords: angular,pydantic,react,schema,typescript,ui,validation,vue
Classifier: Development Status :: 4 - Beta
Classifier: Intended Audience :: Developers
Classifier: License :: OSI Approved :: MIT License
Classifier: Operating System :: OS Independent
Classifier: Programming Language :: Python :: 3
Classifier: Programming Language :: Python :: 3.8
Classifier: Programming Language :: Python :: 3.9
Classifier: Programming Language :: Python :: 3.10
Classifier: Programming Language :: Python :: 3.11
Classifier: Programming Language :: Python :: 3.12
Classifier: Programming Language :: Python :: 3.13
Classifier: Topic :: Software Development :: Libraries :: Python Modules
Classifier: Topic :: Software Development :: User Interfaces
Classifier: Typing :: Typed
Requires-Python: >=3.8.1
Requires-Dist: pydantic>=2.0.0
Provides-Extra: dev
Requires-Dist: black>=23.0.0; extra == 'dev'
Requires-Dist: datamodel-code-generator>=0.25.0; extra == 'dev'
Requires-Dist: isort>=5.12.0; extra == 'dev'
Requires-Dist: langsmith>=0.1.147; extra == 'dev'
Requires-Dist: mypy>=1.0.0; extra == 'dev'
Requires-Dist: pytest-cov>=4.0.0; extra == 'dev'
Requires-Dist: pytest>=7.0.0; extra == 'dev'
